Workbook

Sheet ورقة1
C5: Feasibility Analysis - Community Learning & Training Management System (CLTMS)
A7: Type | B7: Current Situation / Considerations | C7: Proposed Solution / Benefits | D7: Feasibility Result
A8: Technical | B8: Course and enrollment data kept in paper forms, spreadsheets and chat groups; no real-time seat availability; no central database. | C8: Responsive web application (Arabic/English) with a MySQL/PostgreSQL database, cloud hosting, daily backups, email/SMS notifications. | D8: ✅ Technically feasible
A9: Operational | B9: Manual registration is slow; queues; difficult to track payments and attendance; some staff may resist change. | C9: Online enrollment, automatic seat control and waiting list, payment records, attendance and certificates; training and one-month parallel run. | D9: ✅ Operationally feasible
A10: Economic | B10: One-time cost about EGP 250,000 (development, hosting setup, training, data migration) and about EGP 100,000 per year to run. | C10: Benefits about EGP 270,000 in Year 1 (admin labor, paper, fewer errors, extra enrollment), growing 8% per year. See sheets ورقة2 and ورقة3. | D10: ="✅ Cost-effective (NPV ≈ EGP "&TEXT(ورقة3!B21,"#,##0")&")" -> ✅ Cost-effective (NPV ≈ EGP 478,275)
A11: Legal | B11: Learner personal data and payment records must be protected. | C11: Consent, access control and encryption in line with Egypt's Personal Data Protection Law (Law 151 of 2020); licensed payment provider. | D11: ✅ Legally feasible
A12: Schedule | B12: Registration and reporting depend on manual work and delay the service. | C12: Estimated timeline about 6 months (requirements → design → development → testing/data migration → training and go-live). | D12: ✅ Achievable timeline

Sheet ورقة2
C5: All amounts are planning estimates in EGP. Blue = input, black = formula. | H5: Cost–Benefit Analysis – Community Learning & Training Management System (CLTMS) (EGP)
D7: Category | E7: Description | F7: Estimated Cost | G7: Benefits | H7: Estimated Value (per year)
D8: Software | E8: Analysis, design, development and testing of the web system (one-time) | F8: 180000 | G8: Online catalog and enrollment replace manual registration and reporting. | H8: 120000
D9: Hardware / hosting setup | E9: Cloud server setup, backups, staff devices (one-time) | F9: 30000 | G9: Fewer enrollment and payment errors; service available all the time. | H9: 30000
D10: Training | E10: Staff and trainer workshops and user guides (one-time) | F10: 20000 | G10: Smooth transition; staff use the system efficiently. | H10: Included in other benefits
D11: Data migration | E11: Moving existing learner and course records from spreadsheets (one-time) | F11: 20000 | G11: All records available from day one. | H11: Included in other benefits
D12: Maintenance and running costs | E12: Hosting, support, licenses/SMS, administrator time (per year) | F12: 100000 | G12: Keeps the system reliable and secure. | H12: -
D13: Administration | E13: Current manual system: paper forms, printing, notices | F13: - | G13: Eliminated with CLTMS → mostly paperless. | H13: 20000
D14: Enrollment revenue | E14: Extra learners reached online (about 200 × EGP 500) | F14: - | G14: Wider reach and easier enrollment. | H14: 100000
D15: User Experience | E15: Queues and phone calls waste learners' time | F15: - | G15: Faster access to courses, better satisfaction and reputation. | H15: Intangible but high value
D16: Total (first year) | F16: =SUM(F8:F15) -> 350000 | H16: =SUM(H8:H15) -> 270000
H18: Summary
H20: Total estimated costs (first year, EGP) | I20: =F16 -> 350000
H21: Total estimated annual benefits (Year 1, EGP) | I21: =H16 -> 270000
H22: Payback period (years) | I22: =ورقة3!B24 -> 1.4287245
H23: Net present value over 5 years (EGP) | I23: =ورقة3!B21 -> 478275.48
H24: Conclusion: CLTMS is economically feasible - it pays back in about 1.4 years and has a clearly positive 5-year NPV.

Sheet ورقة3
E1: 5-Year Projection - CLTMS (EGP)
D3: Discount rate | E3: 0.12
D4: Annual benefit growth | E4: 0.08
D5: Annual operating cost growth | E5: 0.05
C6: Assumptions are estimates; change the yellow cells to test other scenarios.
A7: EGP | B7: Year 0 | C7: Year 1 | D7: Year 2 | E7: Year 3 | F7: Year 4 | G7: Year 5
A8: Year index | B8: 0 | C8: 1 | D8: 2 | E8: 3 | F8: 4 | G8: 5
A9: Benefits | B9: 0 | C9: =ورقة2!$H$16*(1+$E$4)^(C$8-1) -> 270000 | D9: =ورقة2!$H$16*(1+$E$4)^(D$8-1) -> 291600 | E9: =ورقة2!$H$16*(1+$E$4)^(E$8-1) -> 314928 | F9: =ورقة2!$H$16*(1+$E$4)^(F$8-1) -> 340122.24 | G9: =ورقة2!$H$16*(1+$E$4)^(G$8-1) -> 367332.02
A10: Development cost (one-time) | B10: =SUM(ورقة2!F8:F11) -> 250000 | C10: 0 | D10: 0 | E10: 0 | F10: 0 | G10: 0
A11: Operating costs | B11: 0 | C11: =ورقة2!$F$12*(1+$E$5)^(C$8-1) -> 100000 | D11: =ورقة2!$F$12*(1+$E$5)^(D$8-1) -> 105000 | E11: =ورقة2!$F$12*(1+$E$5)^(E$8-1) -> 110250 | F11: =ورقة2!$F$12*(1+$E$5)^(F$8-1) -> 115762.5 | G11: =ورقة2!$F$12*(1+$E$5)^(G$8-1) -> 121550.62
A12: Total costs | B12: =B10+B11 -> 250000 | C12: =C10+C11 -> 100000 | D12: =D10+D11 -> 105000 | E12: =E10+E11 -> 110250 | F12: =F10+F11 -> 115762.5 | G12: =G10+G11 -> 121550.62
A13: Net cash flow | B13: =B9-B12 -> -250000 | C13: =C9-C12 -> 170000 | D13: =D9-D12 -> 186600 | E13: =E9-E12 -> 204678 | F13: =F9-F12 -> 224359.74 | G13: =G9-G12 -> 245781.39
A14: Cumulative net cash flow | B14: =B13 -> -250000 | C14: =B14+C13 -> -80000 | D14: =C14+D13 -> 106600 | E14: =D14+E13 -> 311278 | F14: =E14+F13 -> 535637.74 | G14: =F14+G13 -> 781419.13
A15: Discount factor | B15: =1/(1+$E$3)^B$8 -> 1 | C15: =1/(1+$E$3)^C$8 -> 0.89285714 | D15: =1/(1+$E$3)^D$8 -> 0.79719388 | E15: =1/(1+$E$3)^E$8 -> 0.71178025 | F15: =1/(1+$E$3)^F$8 -> 0.63551808 | G15: =1/(1+$E$3)^G$8 -> 0.56742686
A16: PV of benefits | B16: =B9*B15 -> 0 | C16: =C9*C15 -> 241071.43 | D16: =D9*D15 -> 232461.73 | E16: =E9*E15 -> 224159.53 | F16: =F9*F15 -> 216153.83 | G16: =G9*G15 -> 208434.05
A17: PV of costs | B17: =B12*B15 -> 250000 | C17: =C12*C15 -> 89285.714 | D17: =D12*D15 -> 83705.357 | E17: =E12*E15 -> 78473.772 | F17: =F12*F15 -> 73569.162 | G17: =G12*G15 -> 68971.089
A18: PV of net cash flow | B18: =B13*B15 -> -250000 | C18: =C13*C15 -> 151785.71 | D18: =D13*D15 -> 148756.38 | E18: =E13*E15 -> 145685.76 | F18: =F13*F15 -> 142584.67 | G18: =G13*G15 -> 139462.96
A19: Payback helper (years) | B19: 0 | C19: =IF(AND(B14<0,C14>=0),C$8-1+(-B14)/C13,0) -> 0 | D19: =IF(AND(C14<0,D14>=0),D$8-1+(-C14)/D13,0) -> 1.4287245 | E19: =IF(AND(D14<0,E14>=0),E$8-1+(-D14)/E13,0) -> 0 | F19: =IF(AND(E14<0,F14>=0),F$8-1+(-E14)/F13,0) -> 0 | G19: =IF(AND(F14<0,G14>=0),G$8-1+(-F14)/G13,0) -> 0
A21: Net present value (NPV, EGP) | B21: =SUM(B18:G18) -> 478275.48
A22: Return on investment (ROI, PV basis) | B22: =(SUM(B16:G16)-SUM(B17:G17))/SUM(B17:G17) -> 0.74265792
A23: Internal rate of return (IRR) | B23: =IRR(B13:G13) -> 0.70124528
A24: Payback period (years) | B24: =SUM(C19:G19) -> 1.4287245
